flask_redis_cache/__init__.py
flask_redis_cache-0.1.2.dist-info/LICENSE
flask_redis_cache-0.1.2.dist-info/METADATA
flask_redis_cache-0.1.2.dist-info/WHEEL
flask_redis_cache-0.1.2.dist-info/RECORD
