Metadata-Version: 2.3
Name: flask-redis-cache
Version: 0.1.2
Summary: 
Author: codeif
Author-email: me@codeif.com
Requires-Python: >=3.10
Classifier: Programming Language :: Python :: 3
Classifier: Programming Language :: Python :: 3.10
Classifier: Programming Language :: Python :: 3.11
Classifier: Programming Language :: Python :: 3.12
Classifier: Programming Language :: Python :: 3.13
Requires-Dist: flask (>=1)
Requires-Dist: redis[hiredis] (>=6.0)
